{"is_source_file": true, "format": "JavaScript", "description": "Test setup configuration file for frontend using jest-dom matchers to enhance DOM assertions in testing environment.", "external_files": ["@testing-library/jest-dom"], "external_methods": [], "published": ["expect().toHaveTextContent"], "classes": [], "methods": [], "calls": ["import '@testing-library/jest-dom'"], "search-terms": ["jest-dom", "setupTests", "testing-library", "jest", "DOM matchers"], "state": 2, "file_id": 9, "knowledge_revision": 25, "git_revision": "c9570888aa0780df32dace918a744b752dbb3bd1", "ctags": [], "hash": "1a77571e1a8cf36018a41bcedf60db75", "format-version": 4, "code-base-name": "food_app_frontend", "filename": "food_app_frontend/src/setupTests.js", "revision_history": [{"25": "c9570888aa0780df32dace918a744b752dbb3bd1"}]}